{
  "type": "crafting_shaped",
  "skill": "provisioning",
  "research": "icing",
  "tool_type": "spoon",
  "is_tool_recipe": false,
  "block_tier": -1,
  "craft_time": 10,
  "tool_tier": -1,
  "experience": 0,
  "sound": "minecraft:block.wood.step",
  "pattern": [
    " J  ",
    "SES ",
    " C  ",
    "    "
  ],
  "key": {
    "S": {
      "item": "minefantasyreborn:sugar_pot"
    },
    "C": {
      "item": "minefantasyreborn:clay_pot"
    },
    "E": {
      "item": "minecraft:egg"
    },
    "J": {
      "item": "minefantasyreborn:jug_milk"
    }
  },
  "result": {
    "item": "minefantasyreborn:custard"
  }
}