{
  "type": "ShapedAnvilRecipes",
  "skill": "engineering",
  "research": "etools",
  "tool_type": "hammer",
  "is_tool_recipe": false,
  "anvil_tier": 3,
  "recipe_time": 14,
  "recipe_hammer": 3,
  "output_hot": true,
  "pattern": [
    " E    ",
    "SIS   ",
    " S    ",
    " S    "
  ],
  "key": {
    "I": {
      "nbt": "{mf_custom_materials:{main_material:\"iron\"}}",
      "item": "minefantasyreforged:bar"
    },
    "E": {
      "item": "minefantasyreforged:engin_anvil_tools"
    },
    "S": {
      "nbt": "{mf_custom_materials:{main_material:\"steel\"}}",
      "item": "minefantasyreforged:metal_hunk"
    }
  },
  "result": {
    "item": "minefantasyreforged:bolt",
    "count": 2
  }
}