{
    "type": "ShapedAnvilRecipes",
    "skill": "artisanry",
    "research": "",
    "tool_type": "hammer",
    "is_tool_recipe": false,
    "anvil_tier": -1,
    "recipe_time": 20,
    "recipe_hammer": -1,
    "output_hot": true,
    "pattern": [
        "I     ",
        "      ",
        "      ",
        "      "
    ],
    "key": {
        "I": {
            "item": "minefantasyreborn:mithium_ingot"
        }
    },
    "result": {
        "nbt": "{mf_custom_materials:{main_material:\"mithium\"}}",
        "item": "minefantasyreborn:bar"
    }
}